setup.py
distributions/Binomialdistribution.py
distributions/Gaussiandistribution.py
distributions/Generaldistribution.py
distributions/__init__.py
ds_probability.egg-info/PKG-INFO
ds_probability.egg-info/SOURCES.txt
ds_probability.egg-info/dependency_links.txt
ds_probability.egg-info/not-zip-safe
ds_probability.egg-info/top_level.txt